k3cloud_webapi_sdk/__init__.py
k3cloud_webapi_sdk/main.py
k3cloud_webapi_sdk/sample.py
k3cloud_webapi_sdk/const/__init__.py
k3cloud_webapi_sdk/const/const_define.py
k3cloud_webapi_sdk/const/header_param.py
k3cloud_webapi_sdk/core/__init__.py
k3cloud_webapi_sdk/core/webapi_client.py
k3cloud_webapi_sdk/model/__init__.py
k3cloud_webapi_sdk/model/api_config.py
k3cloud_webapi_sdk/model/cookie.py
k3cloud_webapi_sdk/model/cookie_store.py
k3cloud_webapi_sdk/model/identity.py
k3cloud_webapi_sdk/model/query_param.py
k3cloud_webapi_sdk/util/__init__.py
k3cloud_webapi_sdk/util/base64_util.py
k3cloud_webapi_sdk/util/config_util.py
k3cloud_webapi_sdk/util/encode_util.py
k3cloud_webapi_sdk/util/hmac_util.py
kingdee.cdp.webapi.sdk-8.0.4.dist-info/METADATA
kingdee.cdp.webapi.sdk-8.0.4.dist-info/WHEEL
kingdee.cdp.webapi.sdk-8.0.4.dist-info/top_level.txt
kingdee.cdp.webapi.sdk-8.0.4.dist-info/RECORD
