Metadata-Version: 2.1
Name: kingdee.cdp.webapi.sdk
Version: 8.0.4
Summary: python sdk for k3cloud web api v3.0
Home-page: https://open.kingdee.com
Author: g_wang
Author-email: 1249350176@qq.com
License: MIT License
Keywords: k3cloud webapi sdk
Platform: UNKNOWN
Classifier: Development Status :: 4 - Beta
Classifier: Intended Audience :: Developers
Classifier: Topic :: Software Development :: Build Tools
Classifier: License :: OSI Approved :: MIT License
Classifier: Programming Language :: Python :: 3 :: Only
Requires-Dist: requests
Requires-Dist: urllib3
